smsframework_amazon_sns/__init__.py
smsframework_amazon_sns/error.py
smsframework_amazon_sns/provider.py
smsframework_amazon_sns-0.0.2.dist-info/LICENSE
smsframework_amazon_sns-0.0.2.dist-info/METADATA
smsframework_amazon_sns-0.0.2.dist-info/WHEEL
smsframework_amazon_sns-0.0.2.dist-info/top_level.txt
smsframework_amazon_sns-0.0.2.dist-info/RECORD
