Metadata-Version: 2.1
Name: smsframework-amazon-sns
Version: 0.0.2
Summary: SMS framework: Amazon SNS provider 
Home-page: https://github.com/kolypto/py-smsframework-amazon-sns
Author: Mark Vartanyan
Author-email: kolypto@gmail.com
License: BSD
Keywords: sms,message,notification,receive,send,amazon,sns
Platform: any
Classifier: Development Status :: 5 - Production/Stable
Classifier: Intended Audience :: Developers
Classifier: Natural Language :: English
Classifier: Programming Language :: Python :: 2
Classifier: Programming Language :: Python :: 3
Classifier: Operating System :: OS Independent
Requires-Dist: smsframework (>=0.0.9)
Requires-Dist: boto3 (>=1.4)
Provides-Extra: receiver
Requires-Dist: flask (>=0.10) ; extra == 'receiver'
